obogo/__init__.py
obogo/io_obo.py
obogo/obo_reader.py
obogo/statistics.py
obogo/tree.py
obogo/type_checkers.py
obogo/bin/ora.py
obogo-0.4.0.dist-info/METADATA
obogo-0.4.0.dist-info/WHEEL
obogo-0.4.0.dist-info/entry_points.txt
obogo-0.4.0.dist-info/licenses/LICENSE
obogo-0.4.0.dist-info/RECORD
