Metadata-Version: 2.4
Name: obogo
Version: 0.4.0
Summary: Yet another ontology crawler to perform ORA!!!
License-File: LICENSE
Requires-Python: >=3.12
Requires-Dist: networkx>=3.2.1
Requires-Dist: pyproteinsext>=3.1.6
Requires-Dist: scipy>=1.11.3
Requires-Dist: uniprot-redis>=1.8.3
